solnlib/__init__.py
solnlib/_utils.py
solnlib/acl.py
solnlib/alerts_rest_client.py
solnlib/bulletin_rest_client.py
solnlib/concurrent/concurrent_executor.py
solnlib/concurrent/process_pool.py
solnlib/concurrent/thread_pool.py
solnlib/conf_manager.py
solnlib/credentials.py
solnlib/file_monitor.py
solnlib/hec_config.py
solnlib/log.py
solnlib/modular_input/__init__.py
solnlib/modular_input/checkpointer.py
solnlib/modular_input/event.py
solnlib/modular_input/event_writer.py
solnlib/modular_input/modinput.py
solnlib/modular_input/modular_input.py
solnlib/net_utils.py
solnlib/orphan_process_monitor.py
solnlib/pattern.py
solnlib/rest.py
solnlib/schedule/job.py
solnlib/schedule/scheduler.py
solnlib/server_info.py
solnlib/soln_exceptions.py
solnlib/splunk_rest_client.py
solnlib/splunkenv.py
solnlib/time_parser.py
solnlib/timer_queue.py
solnlib/user_access.py
solnlib/utils.py
solnlib-6.2.0.dist-info/LICENSE
solnlib-6.2.0.dist-info/METADATA
solnlib-6.2.0.dist-info/WHEEL
solnlib-6.2.0.dist-info/RECORD
